outpak/__init__.py
outpak/__main__.py
outpak/main.py
outpak/run.py
outpak-1.0.0.dev1247.dist-info/DESCRIPTION.rst
outpak-1.0.0.dev1247.dist-info/METADATA
outpak-1.0.0.dev1247.dist-info/RECORD
outpak-1.0.0.dev1247.dist-info/WHEEL
outpak-1.0.0.dev1247.dist-info/entry_points.txt
outpak-1.0.0.dev1247.dist-info/metadata.json
outpak-1.0.0.dev1247.dist-info/top_level.txt
