Metadata-Version: 2.0
Name: outpak
Version: 1.0.0.dev1247
Summary: PIP install wrapper for Git Personal Token
Home-page: UNKNOWN
Author: Chris Maillefaud
Author-email: UNKNOWN
License: UNKNOWN
Keywords: pip install git personal token
Platform: UNKNOWN
Classifier: Development Status :: 4 - Beta
Classifier: Intended Audience :: Developers
Classifier: Topic :: Software Development :: User Interfaces
Classifier: Programming Language :: Python :: 2.7
Classifier: Programming Language :: Python :: 3.5
Classifier: Programming Language :: Python :: 3.6
Requires-Dist: buzio
Requires-Dist: docopt
Requires-Dist: PyYAML
